daytum_cat/__init__.py
daytum_cat/petrophysical.yaml
daytum_cat/siesmic.yaml
daytum_cat/us_production.yaml
daytum_cat/us_wells.yaml
daytum_cat/data/1D_Porosity.csv
daytum_cat/data/2D_MV_200wells.csv
daytum_cat/data/AI_grid.csv
daytum_cat/data/Density_Por_data.csv
daytum_cat/data/ND_production.csv
daytum_cat/data/nonlinear_facies_v1.csv
daytum_cat/data/nonlinear_facies_v2.csv
daytum_cat/data/poro_perm.csv
daytum_cat/data/random_parabola.csv
daytum_cat/data/sample_data.csv
daytum_cat/data/sample_data_12.csv
daytum_cat/data/sample_data_MV_biased.csv
daytum_cat/data/sample_data_biased.csv
daytum_cat/data/stochastic_poro_perm.csv
daytum_cat/data/unconv_MV.csv
daytum_cat/data/unconv_MV_v2.csv
daytum_cat/data/unconv_MV_v4.csv
daytum_data-0.2.14.dist-info/LICENSE
daytum_data-0.2.14.dist-info/METADATA
daytum_data-0.2.14.dist-info/WHEEL
daytum_data-0.2.14.dist-info/entry_points.txt
daytum_data-0.2.14.dist-info/top_level.txt
daytum_data-0.2.14.dist-info/RECORD
