Metadata-Version: 2.1
Name: daytum-data
Version: 0.2.14
Summary: Intake data package for Daytum classes
Home-page: https://github.com/daytum/intake-data
Author: John T. Foster
Author-email: john@daytum.io
License: UNKNOWN
Platform: UNKNOWN
License-File: LICENSE
Requires-Dist: intake (>=0.5.5)
Requires-Dist: intake-sql
Requires-Dist: psycopg2-binary
